hptas/__init__.py
hptas/annotation.py
hptas/component.py
hptas/db.py
hptas/message.py
hptas/phasing.py
hptas/program.py
hptas-1.0.0.dist-info/LICENSE
hptas-1.0.0.dist-info/METADATA
hptas-1.0.0.dist-info/WHEEL
hptas-1.0.0.dist-info/entry_points.txt
hptas-1.0.0.dist-info/top_level.txt
hptas-1.0.0.dist-info/RECORD
