Metadata-Version: 2.1
Name: hptas
Version: 1.0.0
Summary: A library for haplotype phasing using transcriptome information and RNA-seq data.
Home-page: https://github.com/wjnjlcn/hptas
Author: Jianan Wang
Author-email: wjnjlcn@hit.edu.cn
Classifier: Programming Language :: Python :: 3
Classifier: License :: OSI Approved :: GNU General Public License v3 (GPLv3)
Classifier: Operating System :: OS Independent
Requires-Python: >=3.7
License-File: LICENSE
